[{"id":"fae1ce9a-848d-479b-b059-e93cb026cdf9","userId":"326a3369-78fc-44e7-ad52-03e97371ca72","name":"primary","balances":[{"availableBalance":"10.00000000","totalBalance":"20.00000000","currency":"USD"},{"availableBalance":"0.00000000","totalBalance":"0.00000000","currency":"XBT"},{"availableBalance":"0.00000000","totalBalance":"0.00000000","currency":"EUR"},{"availableBalance":"0.00000000","totalBalance":"0.00000000","currency":"SGD"}],"accountIdentifier":"PRIVATEBETA55-2285-2HN"},{"id":"ff011d0a-c3e0-45f2-8919-5f6b8b1d8c5a","userId":"326a3369-78fc-44e7-ad52-03e97371ca72","name":"secondary","balances":[{"availableBalance":"0.00000000","totalBalance":"0.00000000","currency":"USD"},{"availableBalance":"0.00000000","totalBalance":"0.00000000","currency":"XBT"},{"availableBalance":"0.00000000","totalBalance":"0.00000000","currency":"EUR"},{"availableBalance":"0.00000000","totalBalance":"0.00000000","currency":"SGD"}],"accountIdentifier":"PRIVATEBETA55-2285-2E1"},{"id":"b440efce-a83c-4873-8833-802a1022b476","userId":"326a3369-78fc-44e7-ad52-03e97371ca72","name":"Wallet","balances":[{"availableBalance":"98897.00000000","totalBalance":"98897.00000000","currency":"USD"},{"availableBalance":"10006.01500000","totalBalance":"10006.01500000","currency":"XBT"},{"availableBalance":"100456.38207201","totalBalance":"100456.38207201","currency":"EUR"},{"availableBalance":"100000.00000000","totalBalance":"100000.00000000","currency":"SGD"}],"accountIdentifier":"PRIVATEBETA55-2285-26Z"}]
